mortal_work/__init__.py
mortal_work/bonade_main.cpython-37m-x86_64-linux-gnu.so
mortal_work/work_main.cpython-37m-x86_64-linux-gnu.so
mortal_work-4.2.2.dist-info/METADATA
mortal_work-4.2.2.dist-info/WHEEL
mortal_work-4.2.2.dist-info/top_level.txt
mortal_work-4.2.2.dist-info/RECORD
