Metadata-Version: 2.1
Name: mortal-work
Version: 4.2.2
Summary: mortal工具集::mortal_work
Home-page: https://www.example.com
Author: Mortal
Author-email: mortal9098@163.com
License: MIT
Classifier: Development Status :: 4 - Beta
Classifier: Programming Language :: Python :: 3
Classifier: Programming Language :: Python :: 3.7
Classifier: Operating System :: POSIX :: Linux
Classifier: Intended Audience :: Developers
Requires-Python: >=3.7
Requires-Dist: mortal-crypt
Requires-Dist: mortal-curl
Requires-Dist: ms9
